HDL_FPGA/rtl/pdm_decimator.sv
/**
 * @file    pdm_decimator.sv
 * @brief   64:1 PDM to 16-bit PCM Decimator
 *          AgriGuard-RES | Agrionics Systems Co.
 *
 * Architecture: Simple Sinc1 (moving average) + bit growth compensation
 * Decimation ratio: 64
 * Input:  1-bit PDM @ ~3 MHz
 * Output: 16-bit PCM @ ~48 kHz (one pcm_valid pulse every 64 clocks)
 */

`timescale 1ns / 1ps
`default_nettype none

module pdm_decimator (
    input  wire        clk,
    input  wire        rst_n,
    input  wire        pdm_data,
    output logic [15:0] pcm_out,
    output logic        pcm_valid
);

    // =====================================================================
    // Accumulator + Decimation Counter
    // =====================================================================
    logic [6:0]  ones_count;    // Counts number of 1's (0-64)
    logic [5:0]  decim_cnt;     // Counts 0..63

    always_ff @(posedge clk or negedge rst_n) begin
        if (!rst_n) begin
            ones_count  <= '0;
            decim_cnt   <= '0;
            pcm_out     <= '0;
            pcm_valid   <= 1'b0;
        end
        else begin
            pcm_valid <= 1'b0;

            // Count '1's in the PDM bitstream
            if (pdm_data)
                ones_count <= ones_count + 1'd1;

            decim_cnt <= decim_cnt + 1'b1;

            // Decimate every 64 clocks
            if (decim_cnt == 6'd63) begin
                pcm_out   <= saturate(ones_count);
                pcm_valid <= 1'b1;
                
                ones_count <= '0;
                decim_cnt  <= '0;
            end
        end
    end

    // =====================================================================
    // Scaling + Saturation
    // =====================================================================
    function automatic logic [15:0] saturate(input logic [6:0] count);
        logic signed [15:0] pcm_temp;
        
        // Map 0..64 → -32768 .. +32767 (32 ones ≈ 0)
        pcm_temp = $signed(count) * 16'sd1024 - 16'sd32768;

        // Saturate to 16-bit signed range
        if (pcm_temp > 16'sd32767)
            return 16'sd32767;
        else if (pcm_temp < -16'sd32768)
            return 16'sd32768;
        else
            return pcm_temp;
    endfunction

endmodule

`default_nettype wire

HDL_FPGA/HDL_FPGA/tb/tb_pdm_decimator.sv
/**
 * @file    tb_pdm_decimator.sv
 * @brief   PDM Decimator Unit Testbench
 *          AgriGuard-RES | Agrionics Systems Co.
 *
 * Verifies:
 *   1. PCM valid strobe fires every 64 PDM clocks (decimation ratio)
 *   2. DC input (all 1s) → saturates at positive full scale
 *   3. Alternating 1/0 (silence) → PCM output near zero
 *   4. 8 kHz sigma-delta encoded sine → non-zero PCM output with
 *      correct sign pattern
 *
 * Run:
 *   iverilog -g2012 -o sim/pdm_sim tb/tb_pdm_decimator.sv rtl/pdm_decimator.sv
 *   vvp sim/pdm_sim
 */

`timescale 1ns / 1ps
`default_nettype none

module tb_pdm_decimator;

    // DUT ports
    logic        clk;
    logic        rst_n;
    logic        pdm_data;
    logic [15:0] pcm_out;
    logic        pcm_valid;

    // DUT
    pdm_decimator u_dut (
        .clk      (clk),
        .rst_n    (rst_n),
        .pdm_data (pdm_data),
        .pcm_out  (pcm_out),
        .pcm_valid(pcm_valid)
    );

    // 3 MHz PDM clock (333.33 ns period)
    localparam real PDM_CLK_NS = 333.333;
    initial clk = 1'b0;
    always #(PDM_CLK_NS / 2.0) clk = ~clk;

    // Sigma-delta state
    real sd_accum;
    real sd_phase;
    real sd_input;
    localparam real AUDIO_FREQ  = 8000.0;
    localparam real PDM_CLK_HZ  = 3000000.0;
    localparam real TWO_PI      = 6.283185307;

    // PCM sample counter and checker
    integer pcm_count;
    integer valid_count;

    initial begin
        $dumpfile("sim/pdm_decimator.vcd");
        $dumpvars(0, tb_pdm_decimator);

        // Init
        rst_n    = 1'b0;
        pdm_data = 1'b0;
        sd_accum = 0.0;
        sd_phase = 0.0;
        pcm_count   = 0;
        valid_count = 0;

        // ── TEST 1: Reset ─────────────────────────────────────────────────
        $display("[PDM-TB] Applying reset...");
        repeat(10) @(posedge clk);
        rst_n = 1'b1;
        $display("[PDM-TB] Reset released");

        // ── TEST 2: DC input (all 1s) — expect large positive PCM ─────────
        $display("[PDM-TB] TEST 2: DC full-scale input (all 1s)");
        pdm_data = 1'b1;
        repeat(640) @(posedge clk);  // 10 PCM samples
        $display("[PDM-TB]   Last PCM = 0x%04X (%0d)", pcm_out, $signed(pcm_out));

        // ── TEST 3: Silence (alternating) — expect PCM near zero ──────────
        $display("[PDM-TB] TEST 3: Silence input (alternating 10101...)");
        repeat(640) @(posedge clk) pdm_data = ~pdm_data;
        $display("[PDM-TB]   Last PCM = 0x%04X (%0d)", pcm_out, $signed(pcm_out));

        // ── TEST 4: 8 kHz sigma-delta sine — run 48 PCM samples ───────────
        $display("[PDM-TB] TEST 4: 8 kHz sigma-delta sine (48 PCM samples)");
        sd_accum = 0.5;
        sd_phase = 0.0;

        repeat(48 * 64) @(posedge clk) begin
            // Sigma-delta on every PDM clock
            sd_phase = sd_phase + (TWO_PI * AUDIO_FREQ / PDM_CLK_HZ);
            if (sd_phase > TWO_PI) sd_phase = sd_phase - TWO_PI;
            sd_input = 0.5 + 0.45 * $sin(sd_phase);
            sd_accum = sd_accum + sd_input;
            if (sd_accum >= 1.0) begin
                pdm_data = 1'b1;
                sd_accum = sd_accum - 1.0;
            end else begin
                pdm_data = 1'b0;
            end

            // Log each valid PCM output
            if (pcm_valid) begin
                valid_count = valid_count + 1;
                if (valid_count <= 8 || valid_count >= 44) begin
                    $display("[PDM-TB]   PCM[%0d] = %0d (0x%04X)",
                             valid_count, $signed(pcm_out), pcm_out);
                end
            end
        end

        $display("[PDM-TB] Total valid PCM samples seen: %0d", valid_count);
        $display("[PDM-TB] PDM decimator test complete");
        $finish;
    end

    // Timeout watchdog
    initial begin
        #50000000;
        $display("[PDM-TB] TIMEOUT");
        $finish;
    end

endmodule

`default_nettype wire

HDL_FPGA/sim/pdm_decimator.vcd
$date
	Wed Jun 10 16:30:54 2026
$end
$version
	Icarus Verilog
$end
$timescale
	1ps
$end
$scope module tb_pdm_decimator $end
$var wire 1 ! pcm_valid $end
$var wire 16 " pcm_out [15:0] $end
$var real 1 # AUDIO_FREQ $end
$var real 1 $ PDM_CLK_HZ $end
$var real 1 % PDM_CLK_NS $end
$var real 1 & TWO_PI $end
$var reg 1 ' clk $end
$var reg 1 ( pdm_data $end
$var reg 1 ) rst_n $end
$var integer 32 * pcm_count [31:0] $end
$var real 1 + sd_accum $end
$var real 1 , sd_input $end
$var real 1 - sd_phase $end
$var integer 32 . valid_count [31:0] $end
$scope module u_dut $end
$var wire 1 ' clk $end
$var wire 1 ( pdm_data $end
$var wire 1 ) rst_n $end
$var reg 6 / decim_cnt [5:0] $end
$var reg 7 0 ones_count [6:0] $end
$var reg 16 1 pcm_out [15:0] $end
$var reg 1 ! pcm_valid $end
$scope function saturate $end
$upscope $end
$upscope $end
$upscope $end
$enddefinitions $end
$comment Show the parameter values. $end
$dumpall
r6.283185307 &
r333.333 %
r3000000 $
r8000 #
$end
#0
$dumpvars
b0 1
b0 0
b0 /
b0 .
r0 -
r0 ,
r0 +
b0 *
0)
0(
0'
b0 "
0!
$end
#166667
1'
#333334
0'
#500001
1'
#666668
0'
#833335
1'
#1000002
0'
#1166669
1'
#1333336
0'
#1500003
1'
#1666670
0'
#1833337
1'
#2000004
0'
#2166671
1'
#2333338
0'
#2500005
1'
#2666672
0'
#2833339
1'
#3000006
0'
#3166673
b1 /
b1 0
1(
1)
1'
#3333340
0'
#3500007
b10 /
b10 0
1'
#3666674
0'
#3833341
b11 /
b11 0
1'
#4000008
0'
#4166675
b100 /
b100 0
1'
#4333342
0'
#4500009
b101 /
b101 0
1'
#4666676
0'
#4833343
b110 /
b110 0
1'
#5000010
0'
#5166677
b111 /
b111 0
1'
#5333344
0'
#5500011
b1000 /
b1000 0
1'
#5666678
0'
#5833345
b1001 /
b1001 0
1'
#6000012
0'
#6166679
b1010 /
b1010 0
1'
#6333346
0'
#6500013
b1011 /
b1011 0
1'
#6666680
0'
#6833347
b1100 /
b1100 0
1'
#7000014
0'
#7166681
b1101 /
b1101 0
1'
#7333348
0'
#7500015
b1110 /
b1110 0
1'
#7666682
0'
#7833349
b1111 /
b1111 0
1'
#8000016
0'
#8166683
b10000 /
b10000 0
1'
#8333350
0'
#8500017
b10001 /
b10001 0
1'
#8666684
0'
#8833351
b10010 /
b10010 0
1'
#9000018
0'
#9166685
b10011 /
b10011 0
1'
#9333352
0'
#9500019
b10100 /
b10100 0
1'
#9666686
0'
#9833353
b10101 /
b10101 0
1'
#10000020
0'
#10166687
b10110 /
b10110 0
1'
#10333354
0'
#10500021
b10111 /
b10111 0
1'
#10666688
0'
#10833355
b11000 /
b11000 0
1'
#11000022
0'
#11166689
b11001 /
b11001 0
1'
#11333356
0'
#11500023
b11010 /
b11010 0
1'
#11666690
0'
#11833357
b11011 /
b11011 0
1'
#12000024
0'
#12166691
b11100 /
b11100 0
1'
#12333358
0'
#12500025
b11101 /
b11101 0
1'
#12666692
0'
#12833359
b11110 /
b11110 0
1'
#13000026
0'
#13166693
b11111 /
b11111 0
1'
#13333360
0'
#13500027
b100000 /
b100000 0
1'
#13666694
0'
#13833361
b100001 /
b100001 0
1'
#14000028
0'
#14166695
b100010 /
b100010 0
1'
#14333362
0'
#14500029
b100011 /
b100011 0
1'
#14666696
0'
#14833363
b100100 /
b100100 0
1'
#15000030
0'
#15166697
b100101 /
b100101 0
1'
#15333364
0'
#15500031
b100110 /
b100110 0
1'
#15666698
0'
#15833365
b100111 /
b100111 0
1'
#16000032
0'
#16166699
b101000 /
b101000 0
1'
#16333366
0'
#16500033
b101001 /
b101001 0
1'
#16666700
0'
#16833367
b101010 /
b101010 0
1'
#17000034
0'
#17166701
b101011 /
b101011 0
1'
#17333368
0'
#17500035
b101100 /
b101100 0
1'
#17666702
0'
#17833369
b101101 /
b101101 0
1'
#18000036
0'
#18166703
b101110 /
b101110 0
1'
#18333370
0'
#18500037
b101111 /
b101111 0
1'
#18666704
0'
#18833371
b110000 /
b110000 0
1'
#19000038
0'
#19166705
b110001 /
b110001 0
1'
#19333372
0'
#19500039
b110010 /
b110010 0
1'
#19666706
0'
#19833373
b110011 /
b110011 0
1'
#20000040
0'
#20166707
b110100 /
b110100 0
1'
#20333374
0'
#20500041
b110101 /
b110101 0
1'
#20666708
0'
#20833375
b110110 /
b110110 0
1'
#21000042
0'
#21166709
b110111 /
b110111 0
1'
#21333376
0'
#21500043
b111000 /
b111000 0
1'
#21666710
0'
#21833377
b111001 /
b111001 0
1'
#22000044
0'
#22166711
b111010 /
b111010 0
1'
#22333378
0'
#22500045
b111011 /
b111011 0
1'
#22666712
0'
#22833379
b111100 /
b111100 0
1'
#23000046
0'
#23166713
b111101 /
b111101 0
1'
#23333380
0'
#23500047
b111110 /
b111110 0
1'
#23666714
0'
#23833381
b111111 /
b111111 0
1'
#24000048
0'
#24166715
1!
b111110000000000 "
b111110000000000 1
b0 /
b0 0
1'
#24333382
0'
#24500049
b1 /
b1 0
0!
1'
#24666716
0'
#24833383
b10 /
b10 0
1'
#25000050
0'
#25166717
b11 /
b11 0
1'
#25333384
0'
#25500051
b100 /
b100 0
1'
#25666718
0'
#25833385
b101 /
b101 0
1'
#26000052
0'
#26166719
b110 /
b110 0
1'
#26333386
0'
#26500053
b111 /
b111 0
1'
#26666720
0'
#26833387
b1000 /
b1000 0
1'
#27000054
0'
#27166721
b1001 /
b1001 0
1'
#27333388
0'
#27500055
b1010 /
b1010 0
1'
#27666722
0'
#27833389
b1011 /
b1011 0
1'
#28000056
0'
#28166723
b1100 /
b1100 0
1'
#28333390
0'
#28500057
b1101 /
b1101 0
1'
#28666724
0'
#28833391
b1110 /
b1110 0
1'
#29000058
0'
#29166725
b1111 /
b1111 0
1'
#29333392
0'
#29500059
b10000 /
b10000 0
1'
#29666726
0'
#29833393
b10001 /
b10001 0
1'
#30000060
0'
#30166727
b10010 /
b10010 0
1'
#30333394
0'
#30500061
b10011 /
b10011 0
1'
#30666728
0'
#30833395
b10100 /
b10100 0
1'
#31000062
0'
#31166729
b10101 /
b10101 0
1'
#31333396
0'
#31500063
b10110 /
b10110 0
1'
#31666730
0'
#31833397
b10111 /
b10111 0
1'
#32000064
0'
#32166731
b11000 /
b11000 0
1'
#32333398
0'
#32500065
b11001 /
b11001 0
1'
#32666732
0'
#32833399
b11010 /
b11010 0
1'
#33000066
0'
#33166733
b11011 /
b11011 0
1'
#33333400
0'
#33500067
b11100 /
b11100 0
1'
#33666734
0'
#33833401
b11101 /
b11101 0
1'
#34000068
0'
#34166735
b11110 /
b11110 0
1'
#34333402
0'
#34500069
b11111 /
b11111 0
1'
#34666736
0'
#34833403
b100000 /
b100000 0
1'
#35000070
0'
#35166737
b100001 /
b100001 0
1'
#35333404
0'
#35500071
b100010 /
b100010 0
1'
#35666738
0'
#35833405
b100011 /
b100011 0
1'
#36000072
0'
#36166739
b100100 /
b100100 0
1'
#36333406
0'
#36500073
b100101 /
b100101 0
1'
#36666740
0'
#36833407
b100110 /
b100110 0
1'
#37000074
0'
#37166741
b100111 /
b100111 0
1'
#37333408
0'
#37500075
b101000 /
b101000 0
1'
#37666742
0'
#37833409
b101001 /
b101001 0
1'
#38000076
0'
#38166743
b101010 /
b101010 0
1'
#38333410
0'
#38500077
b101011 /
b101011 0
1'
#38666744
0'
#38833411
b101100 /
b101100 0
1'
#39000078
0'
#39166745
b101101 /
b101101 0
1'
#39333412
0'
#39500079
b101110 /
b101110 0
1'
#39666746
0'
#39833413
b101111 /
b101111 0
1'
#40000080
0'
#40166747
b110000 /
b110000 0
1'
#40333414
0'
#40500081
b110001 /
b110001 0
1'
#40666748
0'
#40833415
b110010 /
b110010 0
1'
#41000082
0'
#41166749
b110011 /
b110011 0
1'
#41333416
0'
#41500083
b110100 /
b110100 0
1'
#41666750
0'
#41833417
b110101 /
b110101 0
1'
#42000084
0'
#42166751
b110110 /
b110110 0
1'
#42333418
0'
#42500085
b110111 /
b110111 0
1'
#42666752
0'
#42833419
b111000 /
b111000 0
1'
#43000086
0'
#43166753
b111001 /
b111001 0
1'
#43333420
0'
#43500087
b111010 /
b111010 0
1'
#43666754
0'
#43833421
b111011 /
b111011 0
1'
#44000088
0'
#44166755
b111100 /
b111100 0
1'
#44333422
0'
#44500089
b111101 /
b111101 0
1'
#44666756
0'
#44833423
b111110 /
b111110 0
1'
#45000090
0'
#45166757
b111111 /
b111111 0
1'
#45333424
0'
#45500091
1!
b0 /
b0 0
1'
#45666758
0'
#45833425
b1 /
b1 0
0!
1'
#46000092
0'
#46166759
b10 /
b10 0
1'
#46333426
0'
#46500093
b11 /
b11 0
1'
#46666760
0'
#46833427
b100 /
b100 0
1'
#47000094
0'
#47166761
b101 /
b101 0
1'
#47333428
0'
#47500095
b110 /
b110 0
1'
#47666762
0'
#47833429
b111 /
b111 0
1'
#48000096
0'
#48166763
b1000 /
b1000 0
1'
#48333430
0'
#48500097
b1001 /
b1001 0
1'
#48666764
0'
#48833431
b1010 /
b1010 0
1'
#49000098
0'
#49166765
b1011 /
b1011 0
1'
#49333432
0'
#49500099
b1100 /
b1100 0
1'
#49666766
0'
#49833433
b1101 /
b1101 0
1'
#50000100
0'
#50166767
b1110 /
b1110 0
1'
#50333434
0'
#50500101
b1111 /
b1111 0
1'
#50666768
0'
#50833435
b10000 /
b10000 0
1'
#51000102
0'
#51166769
b10001 /
b10001 0
1'
#51333436
0'
#51500103
b10010 /
b10010 0
1'
#51666770
0'
#51833437
b10011 /
b10011 0
1'
#52000104
0'
#52166771
b10100 /
b10100 0
1'
#52333438
0'
#52500105
b10101 /
b10101 0
1'
#52666772
0'
#52833439
b10110 /
b10110 0
1'
#53000106
0'
#53166773
b10111 /
b10111 0
1'
#53333440
0'
#53500107
b11000 /
b11000 0
1'
#53666774
0'
#53833441
b11001 /
b11001 0
1'
#54000108
0'
#54166775
b11010 /
b11010 0
1'
#54333442
0'
#54500109
b11011 /
b11011 0
1'
#54666776
0'
#54833443
b11100 /
b11100 0
1'
#55000110
0'
#55166777
b11101 /
b11101 0
1'
#55333444
0'
#55500111
b11110 /
b11110 0
1'
#55666778
0'
#55833445
b11111 /
b11111 0
1'
#56000112
0'
#56166779
b100000 /
b100000 0
1'
#56333446
0'
#56500113
b100001 /
b100001 0
1'
#56666780
0'
#56833447
b100010 /
b100010 0
1'
#57000114
0'
#57166781
b100011 /
b100011 0
1'
#57333448
0'
#57500115
b100100 /
b100100 0
1'
#57666782
0'
#57833449
b100101 /
b100101 0
1'
#58000116
0'
#58166783
b100110 /
b100110 0
1'
#58333450
0'
#58500117
b100111 /
b100111 0
1'
#58666784
0'
#58833451
b101000 /
b101000 0
1'
#59000118
0'
#59166785
b101001 /
b101001 0
1'
#59333452
0'
#59500119
b101010 /
b101010 0
1'
#59666786
0'
#59833453
b101011 /
b101011 0
1'
#60000120
0'
#60166787
b101100 /
b101100 0
1'
#60333454
0'
#60500121
b101101 /
b101101 0
1'
#60666788
0'
#60833455
b101110 /
b101110 0
1'
#61000122
0'
#61166789
b101111 /
b101111 0
1'
#61333456
0'
#61500123
b110000 /
b110000 0
1'
#61666790
0'
#61833457
b110001 /
b110001 0
1'
#62000124
0'
#62166791
b110010 /
b110010 0
1'
#62333458
0'
#62500125
b110011 /
b110011 0
1'
#62666792
0'
#62833459
b110100 /
b110100 0
1'
#63000126
0'
#63166793
b110101 /
b110101 0
1'
#63333460
0'
#63500127
b110110 /
b110110 0
1'
#63666794
0'
#63833461
b110111 /
b110111 0
1'
#64000128
0'
#64166795
b111000 /
b111000 0
1'
#64333462
0'
#64500129
b111001 /
b111001 0
1'
#64666796
0'
#64833463
b111010 /
b111010 0
1'
#65000130
0'
#65166797
b111011 /
b111011 0
1'
#65333464
0'
#65500131
b111100 /
b111100 0
1'
#65666798
0'
#65833465
b111101 /
b111101 0
1'
#66000132
0'
#66166799
b111110 /
b111110 0
1'
#66333466
0'
#66500133
b111111 /
b111111 0
1'
#66666800
0'
#66833467
1!
b0 /
b0 0
1'
#67000134
0'
#67166801
b1 /
b1 0
0!
1'
#67333468
0'
#67500135
b10 /
b10 0
1'
#67666802
0'
#67833469
b11 /
b11 0
1'
#68000136
0'
#68166803
b100 /
b100 0
1'
#68333470
0'
#68500137
b101 /
b101 0
1'
#68666804
0'
#68833471
b110 /
b110 0
1'
#69000138
0'
#69166805
b111 /
b111 0
1'
#69333472
0'
#69500139
b1000 /
b1000 0
1'
#69666806
0'
#69833473
b1001 /
b1001 0
1'
#70000140
0'
#70166807
b1010 /
b1010 0
1'
#70333474
0'
#70500141
b1011 /
b1011 0
1'
#70666808
0'
#70833475
b1100 /
b1100 0
1'
#71000142
0'
#71166809
b1101 /
b1101 0
1'
#71333476
0'
#71500143
b1110 /
b1110 0
1'
#71666810
0'
#71833477
b1111 /
b1111 0
1'
#72000144
0'
#72166811
b10000 /
b10000 0
1'
#72333478
0'
#72500145
b10001 /
b10001 0
1'
#72666812
0'
#72833479
b10010 /
b10010 0
1'
#73000146
0'
#73166813
b10011 /
b10011 0
1'
#73333480
0'
#73500147
b10100 /
b10100 0
1'
#73666814
0'
#73833481
b10101 /
b10101 0
1'
#74000148
0'
#74166815
b10110 /
b10110 0
1'
#74333482
0'
#74500149
b10111 /
b10111 0
1'
#74666816
0'
#74833483
b11000 /
b11000 0
1'
#75000150
0'
#75166817
b11001 /
b11001 0
1'
#75333484
0'
#75500151
b11010 /
b11010 0
1'
#75666818
0'
#75833485
b11011 /
b11011 0
1'
#76000152
0'
#76166819
b11100 /
b11100 0
1'
#76333486
0'
#76500153
b11101 /
b11101 0
1'
#76666820
0'
#76833487
b11110 /
b11110 0
1'
#77000154
0'
#77166821
b11111 /
b11111 0
1'
#77333488
0'
#77500155
b100000 /
b100000 0
1'
#77666822
0'
#77833489
b100001 /
b100001 0
1'
#78000156
0'
#78166823
b100010 /
b100010 0
1'
#78333490
0'
#78500157
b100011 /
b100011 0
1'
#78666824
0'
#78833491
b100100 /
b100100 0
1'
#79000158
0'
#79166825
b100101 /
b100101 0
1'
#79333492
0'
#79500159
b100110 /
b100110 0
1'
#79666826
0'
#79833493
b100111 /
b100111 0
1'
#80000160
0'
#80166827
b101000 /
b101000 0
1'
#80333494
0'
#80500161
b101001 /
b101001 0
1'
#80666828
0'
#80833495
b101010 /
b101010 0
1'
#81000162
0'
#81166829
b101011 /
b101011 0
1'
#81333496
0'
#81500163
b101100 /
b101100 0
1'
#81666830
0'
#81833497
b101101 /
b101101 0
1'
#82000164
0'
#82166831
b101110 /
b101110 0
1'
#82333498
0'
#82500165
b101111 /
b101111 0
1'
#82666832
0'
#82833499
b110000 /
b110000 0
1'
#83000166
0'
#83166833
b110001 /
b110001 0
1'
#83333500
0'
#83500167
b110010 /
b110010 0
1'
#83666834
0'
#83833501
b110011 /
b110011 0
1'
#84000168
0'
#84166835
b110100 /
b110100 0
1'
#84333502
0'
#84500169
b110101 /
b110101 0
1'
#84666836
0'
#84833503
b110110 /
b110110 0
1'
#85000170
0'
#85166837
b110111 /
b110111 0
1'
#85333504
0'
#85500171
b111000 /
b111000 0
1'
#85666838
0'
#85833505
b111001 /
b111001 0
1'
#86000172
0'
#86166839
b111010 /
b111010 0
1'
#86333506
0'
#86500173
b111011 /
b111011 0
1'
#86666840
0'
#86833507
b111100 /
b111100 0
1'
#87000174
0'
#87166841
b111101 /
b111101 0
1'
#87333508
0'
#87500175
b111110 /
b111110 0
1'
#87666842
0'
#87833509
b111111 /
b111111 0
1'
#88000176
0'
#88166843
1!
b0 /
b0 0
1'
#88333510
0'
#88500177
b1 /
b1 0
0!
1'
#88666844
0'
#88833511
b10 /
b10 0
1'
#89000178
0'
#89166845
b11 /
b11 0
1'
#89333512
0'
#89500179
b100 /
b100 0
1'
#89666846
0'
#89833513
b101 /
b101 0
1'
#90000180
0'
#90166847
b110 /
b110 0
1'
#90333514
0'
#90500181
b111 /
b111 0
1'
#90666848
0'
#90833515
b1000 /
b1000 0
1'
#91000182
0'
#91166849
b1001 /
b1001 0
1'
#91333516
0'
#91500183
b1010 /
b1010 0
1'
#91666850
0'
#91833517
b1011 /
b1011 0
1'
#92000184
0'
#92166851
b1100 /
b1100 0
1'
#92333518
0'
#92500185
b1101 /
b1101 0
1'
#92666852
0'
#92833519
b1110 /
b1110 0
1'
#93000186
0'
#93166853
b1111 /
b1111 0
1'
#93333520
0'
#93500187
b10000 /
b10000 0
1'
#93666854
0'
#93833521
b10001 /
b10001 0
1'
#94000188
0'
#94166855
b10010 /
b10010 0
1'
#94333522
0'
#94500189
b10011 /
b10011 0
1'
#94666856
0'
#94833523
b10100 /
b10100 0
1'
#95000190
0'
#95166857
b10101 /
b10101 0
1'
#95333524
0'
#95500191
b10110 /
b10110 0
1'
#95666858
0'
#95833525
b10111 /
b10111 0
1'
#96000192
0'
#96166859
b11000 /
b11000 0
1'
#96333526
0'
#96500193
b11001 /
b11001 0
1'
#96666860
0'
#96833527
b11010 /
b11010 0
1'
#97000194
0'
#97166861
b11011 /
b11011 0
1'
#97333528
0'
#97500195
b11100 /
b11100 0
1'
#97666862
0'
#97833529
b11101 /
b11101 0
1'
#98000196
0'
#98166863
b11110 /
b11110 0
1'
#98333530
0'
#98500197
b11111 /
b11111 0
1'
#98666864
0'
#98833531
b100000 /
b100000 0
1'
#99000198
0'
#99166865
b100001 /
b100001 0
1'
#99333532
0'
#99500199
b100010 /
b100010 0
1'
#99666866
0'
#99833533
b100011 /
b100011 0
1'
#100000200
0'
#100166867
b100100 /
b100100 0
1'
#100333534
0'
#100500201
b100101 /
b100101 0
1'
#100666868
0'
#100833535
b100110 /
b100110 0
1'
#101000202
0'
#101166869
b100111 /
b100111 0
1'
#101333536
0'
#101500203
b101000 /
b101000 0
1'
#101666870
0'
#101833537
b101001 /
b101001 0
1'
#102000204
0'
#102166871
b101010 /
b101010 0
1'
#102333538
0'
#102500205
b101011 /
b101011 0
1'
#102666872
0'
#102833539
b101100 /
b101100 0
1'
#103000206
0'
#103166873
b101101 /
b101101 0
1'
#103333540
0'
#103500207
b101110 /
b101110 0
1'
#103666874
0'
#103833541
b101111 /
b101111 0
1'
#104000208
0'
#104166875
b110000 /
b110000 0
1'
#104333542
0'
#104500209
b110001 /
b110001 0
1'
#104666876
0'
#104833543
b110010 /
b110010 0
1'
#105000210
0'
#105166877
b110011 /
b110011 0
1'
#105333544
0'
#105500211
b110100 /
b110100 0
1'
#105666878
0'
#105833545
b110101 /
b110101 0
1'
#106000212
0'
#106166879
b110110 /
b110110 0
1'
#106333546
0'
#106500213
b110111 /
b110111 0
1'
#106666880
0'
#106833547
b111000 /
b111000 0
1'
#107000214
0'
#107166881
b111001 /
b111001 0
1'
#107333548
0'
#107500215
b111010 /
b111010 0
1'
#107666882
0'
#107833549
b111011 /
b111011 0
1'
#108000216
0'
#108166883
b111100 /
b111100 0
1'
#108333550
0'
#108500217
b111101 /
b111101 0
1'
#108666884
0'
#108833551
b111110 /
b111110 0
1'
#109000218
0'
#109166885
b111111 /
b111111 0
1'
#109333552
0'
#109500219
1!
b0 /
b0 0
1'
#109666886
0'
#109833553
b1 /
b1 0
0!
1'
#110000220
0'
#110166887
b10 /
b10 0
1'
#110333554
0'
#110500221
b11 /
b11 0
1'
#110666888
0'
#110833555
b100 /
b100 0
1'
#111000222
0'
#111166889
b101 /
b101 0
1'
#111333556
0'
#111500223
b110 /
b110 0
1'
#111666890
0'
#111833557
b111 /
b111 0
1'
#112000224
0'
#112166891
b1000 /
b1000 0
1'
#112333558
0'
#112500225
b1001 /
b1001 0
1'
#112666892
0'
#112833559
b1010 /
b1010 0
1'
#113000226
0'
#113166893
b1011 /
b1011 0
1'
#113333560
0'
#113500227
b1100 /
b1100 0
1'
#113666894
0'
#113833561
b1101 /
b1101 0
1'
#114000228
0'
#114166895
b1110 /
b1110 0
1'
#114333562
0'
#114500229
b1111 /
b1111 0
1'
#114666896
0'
#114833563
b10000 /
b10000 0
1'
#115000230
0'
#115166897
b10001 /
b10001 0
1'
#115333564
0'
#115500231
b10010 /
b10010 0
1'
#115666898
0'
#115833565
b10011 /
b10011 0
1'
#116000232
0'
#116166899
b10100 /
b10100 0
1'
#116333566
0'
#116500233
b10101 /
b10101 0
1'
#116666900
0'
#116833567
b10110 /
b10110 0
1'
#117000234
0'
#117166901
b10111 /
b10111 0
1'
#117333568
0'
#117500235
b11000 /
b11000 0
1'
#117666902
0'
#117833569
b11001 /
b11001 0
1'
#118000236
0'
#118166903
b11010 /
b11010 0
1'
#118333570
0'
#118500237
b11011 /
b11011 0
1'
#118666904
0'
#118833571
b11100 /
b11100 0
1'
#119000238
0'
#119166905
b11101 /
b11101 0
1'
#119333572
0'
#119500239
b11110 /
b11110 0
1'
#119666906
0'
#119833573
b11111 /
b11111 0
1'
#120000240
0'
#120166907
b100000 /
b100000 0
1'
#120333574
0'
#120500241
b100001 /
b100001 0
1'
#120666908
0'
#120833575
b100010 /
b100010 0
1'
#121000242
0'
#121166909
b100011 /
b100011 0
1'
#121333576
0'
#121500243
b100100 /
b100100 0
1'
#121666910
0'
#121833577
b100101 /
b100101 0
1'
#122000244
0'
#122166911
b100110 /
b100110 0
1'
#122333578
0'
#122500245
b100111 /
b100111 0
1'
#122666912
0'
#122833579
b101000 /
b101000 0
1'
#123000246
0'
#123166913
b101001 /
b101001 0
1'
#123333580
0'
#123500247
b101010 /
b101010 0
1'
#123666914
0'
#123833581
b101011 /
b101011 0
1'
#124000248
0'
#124166915
b101100 /
b101100 0
1'
#124333582
0'
#124500249
b101101 /
b101101 0
1'
#124666916
0'
#124833583
b101110 /
b101110 0
1'
#125000250
0'
#125166917
b101111 /
b101111 0
1'
#125333584
0'
#125500251
b110000 /
b110000 0
1'
#125666918
0'
#125833585
b110001 /
b110001 0
1'
#126000252
0'
#126166919
b110010 /
b110010 0
1'
#126333586
0'
#126500253
b110011 /
b110011 0
1'
#126666920
0'
#126833587
b110100 /
b110100 0
1'
#127000254
0'
#127166921
b110101 /
b110101 0
1'
#127333588
0'
#127500255
b110110 /
b110110 0
1'
#127666922
0'
#127833589
b110111 /
b110111 0
1'
#128000256
0'
#128166923
b111000 /
b111000 0
1'
#128333590
0'
#128500257
b111001 /
b111001 0
1'
#128666924
0'
#128833591
b111010 /
b111010 0
1'
#129000258
0'
#129166925
b111011 /
b111011 0
1'
#129333592
0'
#129500259
b111100 /
b111100 0
1'
#129666926
0'
#129833593
b111101 /
b111101 0
1'
#130000260
0'
#130166927
b111110 /
b111110 0
1'
#130333594
0'
#130500261
b111111 /
b111111 0
1'
#130666928
0'
#130833595
1!
b0 /
b0 0
1'
#131000262
0'
#131166929
b1 /
b1 0
0!
1'
#131333596
0'
#131500263
b10 /
b10 0
1'
#131666930
0'
#131833597
b11 /
b11 0
1'
#132000264
0'
#132166931
b100 /
b100 0
1'
#132333598
0'
#132500265
b101 /
b101 0
1'
#132666932
0'
#132833599
b110 /
b110 0
1'
#133000266
0'
#133166933
b111 /
b111 0
1'
#133333600
0'
#133500267
b1000 /
b1000 0
1'
#133666934
0'
#133833601
b1001 /
b1001 0
1'
#134000268
0'
#134166935
b1010 /
b1010 0
1'
#134333602
0'
#134500269
b1011 /
b1011 0
1'
#134666936
0'
#134833603
b1100 /
b1100 0
1'
#135000270
0'
#135166937
b1101 /
b1101 0
1'
#135333604
0'
#135500271
b1110 /
b1110 0
1'
#135666938
0'
#135833605
b1111 /
b1111 0
1'
#136000272
0'
#136166939
b10000 /
b10000 0
1'
#136333606
0'
#136500273
b10001 /
b10001 0
1'
#136666940
0'
#136833607
b10010 /
b10010 0
1'
#137000274
0'
#137166941
b10011 /
b10011 0
1'
#137333608
0'
#137500275
b10100 /
b10100 0
1'
#137666942
0'
#137833609
b10101 /
b10101 0
1'
#138000276
0'
#138166943
b10110 /
b10110 0
1'
#138333610
0'
#138500277
b10111 /
b10111 0
1'
#138666944
0'
#138833611
b11000 /
b11000 0
1'
#139000278
0'
